Metadata-Version: 2.1
Name: telegapi
Version: 0.0
Summary: A wrapper for telegram bot API
Home-page: https://github.com/p0o0uya/telegapi
Author: Pouya Jamali
Author-email: pouyajamali@gmail.com
License: MIT
Project-URL: Bug Tracker, https://github.com/p0o0uya/telegapi/issues
Platform: UNKNOWN
